pydantic_jsonfield/__init__.py
pydantic_jsonfield/apps.py
pydantic_jsonfield/fields.py
pydantic_jsonfield/forms.py
django_pydantic_jsonfield-0.1.2.dist-info/LICENSE
django_pydantic_jsonfield-0.1.2.dist-info/METADATA
django_pydantic_jsonfield-0.1.2.dist-info/WHEEL
django_pydantic_jsonfield-0.1.2.dist-info/top_level.txt
django_pydantic_jsonfield-0.1.2.dist-info/RECORD
