Metadata-Version: 2.1
Name: django-pydantic-jsonfield
Version: 0.1.2
Summary: A Django JSONField extension using Pydantic for data validation.
Author-email: Brian Guggenheimer <bguggs@gmail.com>
License: MIT License
Keywords: django,pydantic,jsonfield
Classifier: Framework :: Django
Classifier: Programming Language :: Python :: 3
Classifier: License :: OSI Approved :: MIT License
License-File: LICENSE
Requires-Dist: Django >=5.0
Requires-Dist: pydantic >=2.0
